{"request_data":[{"RecordedAtTime":"2017-10-27T00:00:17+01:00","acp_ts":1509058817,"ValidUntilTime":"2017-10-27T00:00:17+01:00","VehicleMonitoringRef":"SCNH-15744","acp_id":"SCNH-15744","LineRef":"X4","DirectionRef":"INBOUND","DataFrameRef":"1","DatedVehicleJourneyRef":"1164","PublishedLineName":"X4","OperatorRef":"SCNH","OriginRef":"300000075GS","OriginName":"George Str Stop A","DestinationRef":"30000018114","DestinationName":"Bus Interchange","OriginAimedDepartureTime":"2017-10-26T23:52:00+01:00","Monitored":"true","InPanic":"0","Longitude":"-0.7356970","acp_lng":-0.735697,"Latitude":"52.4492683","acp_lat":52.4492683,"Bearing":"168","Delay":"-PT35S","VehicleRef":"SCNH-15744"}],"module_name":"feedmaker","module_id":"A","feed_id":"cloudamber.sirivm","filename":"1509058821.620_2017-10-27-00-00-21","filepath":"2017/10/27","ts":1509058821,"msg_type":"feed_sirivm"}